devsecrets/__init__.py
devsecrets/interface.py
devsecrets/version.py
devsecrets-0.1.dist-info/LICENSE.txt
devsecrets-0.1.dist-info/METADATA
devsecrets-0.1.dist-info/WHEEL
devsecrets-0.1.dist-info/top_level.txt
devsecrets-0.1.dist-info/RECORD
